noqa_runner/__init__.py
noqa_runner/__main__.py
noqa_runner/config.py
noqa_runner/logging_config.py
noqa_runner/application/__init__.py
noqa_runner/application/run_test_session.py
noqa_runner/application/services/__init__.py
noqa_runner/application/services/mobile_service.py
noqa_runner/domain/__init__.py
noqa_runner/domain/exceptions.py
noqa_runner/domain/models/__init__.py
noqa_runner/domain/models/test_info.py
noqa_runner/domain/models/actions/__init__.py
noqa_runner/domain/models/actions/action_data.py
noqa_runner/domain/models/actions/activate_app.py
noqa_runner/domain/models/actions/background_app.py
noqa_runner/domain/models/actions/base.py
noqa_runner/domain/models/actions/handle_system_alert.py
noqa_runner/domain/models/actions/input_text.py
noqa_runner/domain/models/actions/open_url.py
noqa_runner/domain/models/actions/restart_app.py
noqa_runner/domain/models/actions/scroll.py
noqa_runner/domain/models/actions/stop.py
noqa_runner/domain/models/actions/swipe.py
noqa_runner/domain/models/actions/tap.py
noqa_runner/domain/models/actions/terminate_app.py
noqa_runner/domain/models/actions/wait.py
noqa_runner/domain/models/state/__init__.py
noqa_runner/domain/models/state/condition.py
noqa_runner/domain/models/state/screen.py
noqa_runner/domain/models/state/step.py
noqa_runner/domain/models/state/test_state.py
noqa_runner/infrastructure/__init__.py
noqa_runner/infrastructure/adapters/http/__init__.py
noqa_runner/infrastructure/adapters/http/agent_api.py
noqa_runner/infrastructure/adapters/http/base_client.py
noqa_runner/infrastructure/adapters/http/client_manager.py
noqa_runner/infrastructure/adapters/http/generic.py
noqa_runner/infrastructure/adapters/mobile/__init__.py
noqa_runner/infrastructure/adapters/mobile/appium_adapter.py
noqa_runner/infrastructure/adapters/storage/__init__.py
noqa_runner/infrastructure/adapters/storage/local_storage_adapter.py
noqa_runner/interfaces/__init__.py
noqa_runner/interfaces/cli/__init__.py
noqa_runner-0.2.8.dist-info/METADATA
noqa_runner-0.2.8.dist-info/WHEEL
noqa_runner-0.2.8.dist-info/entry_points.txt
noqa_runner-0.2.8.dist-info/RECORD
