Metadata-Version: 2.4
Name: noqa-runner
Version: 0.2.8
Summary: noqa runner
Author-email: Sergey Ustinov <sergey@noqa.ai>
Requires-Python: >=3.10
Requires-Dist: aiofiles>=24.0.0
Requires-Dist: appium-python-client>=4.0.0
Requires-Dist: defusedxml>=0.7.1
Requires-Dist: httpx[http2]>=0.27.0
Requires-Dist: numpy>=1.24.0
Requires-Dist: pillow>=10.0.0
Requires-Dist: pydantic-settings>=2.10.0
Requires-Dist: pydantic>=2.0.0
Requires-Dist: python-slugify>=8.0.0
Requires-Dist: sentry-sdk>=2.44.0
Requires-Dist: structlog>=24.0.0
Requires-Dist: tenacity>=8.0.0
Requires-Dist: typer>=0.12.0
